pgnparse/__init__.py
pgnparse/py.typed
pgnparse-0.4.0.dist-info/METADATA
pgnparse-0.4.0.dist-info/WHEEL
pgnparse-0.4.0.dist-info/licenses/LICENSE.txt
pgnparse-0.4.0.dist-info/RECORD
