Metadata-Version: 2.4
Name: pgnparse
Version: 0.4.0
Summary: A library for parsing PGN chess notations
Project-URL: Documentation, https://github.com/ItsDrike/pgnparse
Project-URL: Source code, https://github.com/ItsDrike/pgnparse
Author-email: ItsDrike <itsdrike@protonmail.com>
License-Expression: MIT
License-File: LICENSE.txt
Keywords: Chess,PGN,Parsing
Classifier: Development Status :: 4 - Beta
Classifier: Intended Audience :: Developers
Classifier: License :: OSI Approved :: MIT License
Classifier: Natural Language :: English
Classifier: Operating System :: OS Independent
Classifier: Programming Language :: Python
Classifier: Programming Language :: Python :: 3
Classifier: Programming Language :: Python :: 3.12
Classifier: Programming Language :: Python :: 3.13
Classifier: Topic :: Games/Entertainment :: Board Games
Classifier: Topic :: Software Development :: Libraries
Classifier: Topic :: Software Development :: Libraries :: Python Modules
Classifier: Topic :: Text Processing
Classifier: Typing :: Typed
Requires-Python: >=3.12
Requires-Dist: lark>=1.2.2
